<?xml version="1.0" encoding="UTF-8"?>
<song>

<thainame>none</thainame>
<englishname>He Is Exalted</englishname>
<mienthainame>none</mienthainame>
<order>verse1,chorus</order>

<thai>

</thai>

<english>
    <verse1>He is exalted. The King is exalted on high. I will praise Him. He is exalted, forever exalted. And I will praise His name.</verse1>
    <chorus>He is the Lord. Forever His truth shall reign. Heaven and earth. Rejoice in His holy name. He is exalted. The King is exalted on high.</chorus>
</english>
    
<mienthai>

</mienthai>

<chord>

</chord>

</song>