<?xml version="1.0" ?><song>
   <!--Generated from Trang Church Youtube-->
   <thainame>พระองค์อยู่ด้วยโลกคล้ายสวรรค์</thainame>
   <englishname>Where Jesus Is,Tis Heaven</englishname>
   <mienthainame>none</mienthainame>
   <order>verse1,chorus,verse2,chorus,verse3,chorus</order>
   <thai>
      <verse1>เพลงชีวิตคริสเตียน บทที่ 278 พระองค์อยู่ด้วยโลกคล้ายสวรรค์ จัดทำขึ้นเพื่อจะเป็นประโยชน์ให้กับพี่น้องคริสเตียนทุกท่าน  ในการฝึกร้องเพลงชีวิตคริสเตียน</verse1>
      <verse2>ครั้งหนึ่งสวรรค์อยู่ไกลนักหนา แต่เมื่อพระคริสต์ทรงยิ้มกับข้าฯ ความสุขจึงมีภายในวิญญาณ คือสุขสำราญตลอดเวลา</verse2>
      <verse3>อยู่ลุ่มแม่น้ำหรือบนภูเขา อยู่ในวังเจ้าหรือในโรงนา เราอยู่ที่ไหนก็ไม่สำคัญ พระเยซูอยู่ก็คล้ายสวรรค์.</verse3>
      <chorus>โอ้อาเลลูยาข้าฯยินดี เมื่อพระองค์โปรดยกโทษบาปข้าฯ บนบกในน้ำที่ไหนไม่ว่า พระคริสต์อยู่ด้วยนั่นคล้ายสวรรค์</chorus>
   </thai>
   <english>
      <verse1>Music : James M. Black  (Where Jesus Is,Tis Heaven) ผลิตโดย คริสตจักรตรัง www.trangchurch.org</verse1>
      <verse2>Once Heaven seemed a far off place,Till Jesus showed His smiling face;Now it’s begun within my soul,’Twill last while endless ages roll.</verse2>
      <verse3>What matters where on earth we dwell?On mountain top, or in the dell,In cottage, or a mansion fair,Where Jesus is, ’tis Heaven there.</verse3>
      <chorus>O hallelujah, yes, ’tis Heav’n,’Tis Heav’n to know my sins forgiv’n,On land or sea, what matters where?Where Jesus is, ’tis Heaven there.</chorus>
   </english>
   <mienthai>
      <verse1/>
      <verse2/>
      <verse3/>
      <chorus/>
   </mienthai>
   <chord>
      <verse1/>
      <verse2/>
      <verse3/>
      <chorus/>
   </chord>
</song>