<?xml version="1.0" ?>
<song>
	<thainame>ทางเดียว</thainame>
	<englishname>none</englishname>
	<mienthainame>none</mienthainame>
	<order>verse1,chorus1,verse2,verse3</order>
	<thai>
		<verse1>1.ฉันวางชีวิตที่เบื้องพระบาท ทรงเป็นผู้เดียวที่ฉันต้องการ เมื่อกลับคืนมาพระองค์ทรงรอฉันอยู่ เมื่อมีความทุกข์ฉันพึ่งพระองค์ ทรงเป็นผู้เดียวและเป็นที่หนึ่ง  ลูกยอมเป็นทุกสิ่งได้เพื่อพระองค์</verse1>
		<chorus1>*ทางเดียวพระเยซู คือผู้เดียวที่ลูกจะมีชีวิตอยู่ ทางเดียวพระเยซู  คือผู้เดียวที่ลูกจะมีชีวิตอยู่</chorus1>
		<verse2>2.ทรงอยู่ท่ามกลางเราเสมอ  ทุกเวลาและทุกทุกแห่ง  พระคุณล้ำเลิศคุ้มครองชีวิตฉันอยู่  เพราะพระองค์ไม่เคยแปรผัน  ทุกทุกวันยังทรงเหมือนเดิม  ตราบชั่วนิรันดร์ชั่วฟ้าและดินสลาย(*,ข้อ3.)</verse2>
		<verse3>3.ทรงเป็นทางนั้นชีวิตและความจริง  และโดยความเชื่อหาใช่ที่ตามองเห็น  ชีวิตเราเพื่อพระองค์(ซ้ำ4ครั้ง)</verse3>
	</thai>
</song>
