<?xml version="1.0" ?>
<song>
	<thainame>none</thainame>
	<englishname>Cheap shots </englishname>
	<mienthainame>none</mienthainame>
	<order>segment1,segment2,segment3,segment4,segment5,segment6,segment7</order>
	<english>
		<segment1>I have a demon in me. It shows its teeth and escapes. when I impatiently speak. that's when i make my mistakes. It seems I'm prone to abuse. I'm just like you, I'm just like you. I keep my mouth shut around. the fools and liars of this town. Starting fast from their lips. They burned it all to the ground. You know if you want the truth. You'll just end up getting burned too</segment1>
		<segment2>Will the water wash me clean?. You can take it all out on me, you can take it all out on me.</segment2>
		<segment3>So go ahead and spit your poison out. Yeah go ahead and take your cheap shots. I've never been too proud to sin, Why don't you rub my face in it. Yeah go ahead and spit your poison out. Yeah go ahead and take your cheap shots. I've never been too proud to sin, Why don't you rub my face in it.</segment3>
		<segment4>You walk the walk, don't you talk the talk too?. But in your heart you died alone. A long, long time ago.</segment4>
		<segment5>Will the water wash you clean?. You can take it all out on me, you can take it all out on me.</segment5>
		<segment6>So go ahead and spit your poison out. Yeah go ahead and take your cheap shots. I've never been too proud to sin, Why don't you rub my face in it. Yeah go ahead and spit your poison out. Yeah go ahead and take your cheap shots. I've never been too proud to sin, Why don't you rub my face in it.</segment6>
		<segment7>So go ahead and spit your poison out. Yeah go ahead and take your cheap shots. I've never been too proud to sin, Why don't you rub my face in it. Yeah go ahead and spit your poison out. Yeah go ahead and take your cheap shots. I've never been too proud to sin, Why don't you rub my face in it.    </segment7>
	</english>
</song>
