<?xml version="1.0" ?>
<song>
	<thainame>none</thainame>
	<englishname>Faith, Hope And Love </englishname>
	<mienthainame>none</mienthainame>
	<order>segment1,segment2,segment3,segment4,segment5,segment6,segment7</order>
	<english>
		<segment1>A chapter done. Turn the page. And separate roads. Lead separate ways. But as we go, we're not alone. No, we're not alone</segment1>
		<segment2>Because faith and hope and love. Are waiting for you when we say goodbye. Where would we be without the Faith. Where would we be without the Hope. Where would we be without the Faith. The one that God alone has made</segment2>
		<segment3>Because faith and hope and love. Are waiting for you when we say. Faith, hope and love. Are waiting for you when we say goodbye</segment3>
		<segment4>Where would we be without the Faith. Where would we ve without the Hope. Where would we be without the Faith. The one that God alone has made</segment4>
		<segment5>Because faith, hope and love. Are waiting for you when we say. Faith, hope and love. Are waiting for you when we say goodbye</segment5>
		<segment6>Yea, though I walk. Down in the valley of the shadow of darkness. I will not fear. I will fear no evil</segment6>
		<segment7>Because faith, hope and love. Are waiting for you when we say. Faith, hope and love. Are waiting for you when we say goodbye. Because faith and hope and love. Are waiting for you when we say goodbye. Faith and hope and love. Waiting for you when. We'll be praying until then. Waiting for you when we say goodbye    </segment7>
	</english>
</song>
