<?xml version="1.0" ?>
<song>
	<thainame>none</thainame>
	<englishname>Glory Rain Down </englishname>
	<mienthainame>none</mienthainame>
	<order>segment1,segment2,segment3,segment4</order>
	<english>
		<segment1>I want to go where I can know. All of Your mysteries. Leaning on You, being renewed. All for eternity </segment1>
		<segment2>Hallelujah. Hallelujah</segment2>
		<segment3>CHORUS. Glory rain down. Fill up my life. Open the gates. Open the skies. Glory rain down. Fill up my soul. Fill up my soul</segment3>
		<segment4>I want to stay where I can praise. All of Your majesty. Living by faith, loving Your name. All for world to see.     </segment4>
	</english>
</song>
