<?xml version="1.0" ?>
<song>
	<thainame>none</thainame>
	<englishname>Love You So Much </englishname>
	<mienthainame>none</mienthainame>
	<order>segment1,segment2,segment3,segment4</order>
	<english>
		<segment1>Hear these praises from a grateful heart. Each time I think of You. The praises start. Love You so much, Jesus. Love You so much</segment1>
		<segment2>Lord, I love You, my soul sings. In Your presence. Carried on Your wings. Love You so much, Jesus. Love You so much</segment2>
		<segment3>Chorus: How my soul longs for you. Longs to worship You forever. In Your power and majesty. Lift my hands, lift my heart. Lift my voice towards the heavens. For You are my sun and shield</segment3>
		<segment4>(Verse). (Chorus). (1st Verse)    </segment4>
	</english>
</song>
