<?xml version="1.0" ?>
<song>
	<thainame>none</thainame>
	<englishname>Nothing But The Blood   Hillsong </englishname>
	<mienthainame>none</mienthainame>
	<order>segment1,segment2,segment3,segment4,segment5,segment6</order>
	<english>
		<segment1>What can wash away my sin?. Nothing but the blood of Jesus. What can make me whole again?. Nothing but the blood of Jesus</segment1>
		<segment2>Come to us, Lord. You reward those who earnestly, diligently seek You. I wanna see Your face, I wanna know Your way. Come to us, Lord</segment2>
		<segment3>We want You more than this life. More than our way Your way is higher. Your thoughts are higher. We surrender here tonight</segment3>
		<segment4>What can wash away my sin?. Nothing but the blood of Jesus. What can make me whole again?. Nothing but the blood of Jesus</segment4>
		<segment5>Oh, precious is the flow. That makes me white as snow. No other fount I know. Nothing but the blood of Jesus</segment5>
		<segment6>Oh, precious is the flow. That makes me white as snow. No other fount I know. Nothing but the blood of Jesus. Nothing but the blood of Jesus    </segment6>
	</english>
</song>
