<?xml version="1.0" ?>
<song>
	<thainame>none</thainame>
	<englishname>To The Least Of These </englishname>
	<mienthainame>none</mienthainame>
	<order>segment1</order>
	<english>
		<segment1>I will worship You by giving to the poorBy bringing hope to hopeless placesI will love You by feeding those in needBy touching their disease andTheir souls with Your loveYou said what you do to the least of theseYou do it unto meYou know what you do to the least of theseYou do it unto meI WILL LOVE YOU LORD WITH ALL MY HEARTMY SOUL, MY MIND, AND MY STRENGTHAND SO I'LL LOVE THE ONES YOU LOVENOW I'M TAKING UP MY CROSS FOR YOUOBEYING YOUR COMMANDSI WANT MY WORSHIP TO BE TRUE'CAUSE WHEN I'M LOVING THEMI'M LOVING YOUI will honor You by honoring the leastBy giving worth to thingsDeemed worthlessI will serve You by sheltering the strangeBy clothing them with grace thatCannot give in returnHow can I say I love YouWhen I do not love the things that You love?When my heart is hard butYours is broken for this broken worldSo Jesus I will be Your hands and feetDon't just want to sing anymoreI will care for You when I'm caring for the weakWhen I'm going and I'm speakingOf Your love and faithfulnessI will follow You by going where You've beenBy declaring to all men thatYou're the Truth, the Life, the WayOn Judgment Day what will He sayOf the deeds that you have done?    </segment1>
	</english>
</song>
